rflogger/__init__.py
rflogger/logger.py
rflogger-0.0.1.dist-info/LICENSE
rflogger-0.0.1.dist-info/METADATA
rflogger-0.0.1.dist-info/WHEEL
rflogger-0.0.1.dist-info/top_level.txt
rflogger-0.0.1.dist-info/RECORD
