Metadata-Version: 2.1
Name: rflogger
Version: 0.0.1
Summary: Very lightweight yet simple rotating file loggger
Author-email: Juan Ignacio De Nicola <lu4adn@gmail.com>
Project-URL: Homepage, https://github.com/jdenicola/pythonlogger
Project-URL: Issues, https://github.com/jdenicola/pythonlogger/issues
Classifier: Programming Language :: Python :: 3
Classifier: License :: OSI Approved :: MIT License
Classifier: Operating System :: OS Independent
Requires-Python: >=3.8
License-File: LICENSE
